bpm_ai_inference/__init__.py
bpm_ai_inference/classification/__init__.py
bpm_ai_inference/classification/transformers_text_classifier.py
bpm_ai_inference/daemon.py
bpm_ai_inference/image_classification/__init__.py
bpm_ai_inference/image_classification/transformers_image_classifier.py
bpm_ai_inference/llm/__init__.py
bpm_ai_inference/llm/llama_cpp/__init__.py
bpm_ai_inference/llm/llama_cpp/_constants.py
bpm_ai_inference/llm/llama_cpp/llama_chat.py
bpm_ai_inference/llm/llama_cpp/output_schema.prompt
bpm_ai_inference/llm/llama_cpp/tool_use.prompt
bpm_ai_inference/llm/llama_cpp/util.py
bpm_ai_inference/ocr/__init__.py
bpm_ai_inference/ocr/tesseract.py
bpm_ai_inference/pos/__init__.py
bpm_ai_inference/pos/spacy_pos_tagger.py
bpm_ai_inference/question_answering/__init__.py
bpm_ai_inference/question_answering/pix2struct_vqa.py
bpm_ai_inference/question_answering/transformers_docvqa.py
bpm_ai_inference/question_answering/transformers_qa.py
bpm_ai_inference/speech_recognition/__init__.py
bpm_ai_inference/speech_recognition/faster_whisper.py
bpm_ai_inference/token_classification/__init__.py
bpm_ai_inference/token_classification/gliner_token_classifier.py
bpm_ai_inference/token_classification/transformers_token_classifier.py
bpm_ai_inference/translation/__init__.py
bpm_ai_inference/translation/easy_nmt/__init__.py
bpm_ai_inference/translation/easy_nmt/easy_nmt.py
bpm_ai_inference/translation/easy_nmt/opus_mt.py
bpm_ai_inference/translation/easy_nmt/util.py
bpm_ai_inference/util/__init__.py
bpm_ai_inference/util/files.py
bpm_ai_inference/util/hf.py
bpm_ai_inference/util/language.py
bpm_ai_inference/util/optimum.py
bpm_ai_inference-0.3.6.dist-info/LICENSE
bpm_ai_inference-0.3.6.dist-info/METADATA
bpm_ai_inference-0.3.6.dist-info/WHEEL
bpm_ai_inference-0.3.6.dist-info/RECORD
